hybridrouter/__init__.py
hybridrouter/apps.py
hybridrouter/hybridrouter.py
hybridrouter/utils.py
djangorestframework_hybridrouter-1.0.2.dist-info/LICENSE
djangorestframework_hybridrouter-1.0.2.dist-info/METADATA
djangorestframework_hybridrouter-1.0.2.dist-info/WHEEL
djangorestframework_hybridrouter-1.0.2.dist-info/RECORD
