Metadata-Version: 2.1
Name: djangorestframework-hybridrouter
Version: 1.0.2
Summary: Django app that provides a hybrid router for Django Rest Framework
License: MIT
Keywords: django,rest,framework,router,hybrid,views and viewsets
Author: enzo_frnt
Requires-Python: >=3.8,<4
Classifier: Development Status :: 5 - Production/Stable
Classifier: Environment :: Web Environment
Classifier: Framework :: Django
Classifier: Framework :: Django :: 3.2
Classifier: Framework :: Django :: 4.0
Classifier: Framework :: Django :: 4.1
Classifier: Framework :: Django :: 4.2
Classifier: Framework :: Django :: 5.0
Classifier: Framework :: Django :: 5.1
Classifier: Intended Audience :: Developers
Classifier: License :: OSI Approved :: MIT License
Classifier: Operating System :: OS Independent
Classifier: Programming Language :: Python
Classifier: Programming Language :: Python :: 3
Classifier: Programming Language :: Python :: 3.8
Classifier: Programming Language :: Python :: 3.9
Classifier: Programming Language :: Python :: 3.10
Classifier: Programming Language :: Python :: 3.11
Classifier: Programming Language :: Python :: 3.12
Classifier: Programming Language :: Python :: 3.13
Classifier: Programming Language :: Python :: 3 :: Only
Classifier: Topic :: Software Development :: Libraries :: Python Modules
Requires-Dist: django (>=3.2,<5.2)
Requires-Dist: djangorestframework (>=3.12.4,<3.16)
Project-URL: Documentation, https://github.com/enzofrnt/djangorestframework-hybridrouter/blob/main/README.md
Project-URL: Issues, https://github.com/enzofrnt/djangorestframework-hybridrouter/issues
Project-URL: Source Code, https://github.com/enzofrnt/djangorestframework-hybridrouter
